wtte/__init__.py
wtte/data_generators.py
wtte/pipelines.py
wtte/transforms.py
wtte/tte_util.py
wtte/weibull.py
wtte/wtte.py
wtte/objectives/__init__.py
wtte/objectives/tensorflow.py
wtte/plots/__init__.py
wtte/plots/misc.py
wtte/plots/weibull_contour.py
wtte/plots/weibull_heatmap.py
wtte-1.1.1.dist-info/METADATA
wtte-1.1.1.dist-info/RECORD
wtte-1.1.1.dist-info/WHEEL
wtte-1.1.1.dist-info/top_level.txt
