Metadata-Version: 2.1
Name: wtte
Version: 1.1.1
Summary: Weibull Time To Event model. A Deep Learning model for churn- and failure prediction and everything else.
Home-page: https://github.com/ragulpr/wtte-rnn/
Author: Egil Martinsson
Author-email: egil.martinsson@gmail.com
License: MIT
Platform: UNKNOWN
Provides-Extra: test
Provides-Extra: tf_gpu
Provides-Extra: plot
Provides-Extra: dev
Provides-Extra: tf
Provides-Extra: docs
Provides-Extra: build
Requires-Dist: keras (>=2.0)
Requires-Dist: numpy
Requires-Dist: pandas
Requires-Dist: scipy
Requires-Dist: six (==1.10.0)
Provides-Extra: build
Requires-Dist: wheel; extra == 'build'
Requires-Dist: twine; extra == 'build'
Provides-Extra: dev
Requires-Dist: pytest-sugar; extra == 'dev'
Requires-Dist: sphinx; extra == 'dev'
Requires-Dist: sphinx-rtd-theme; extra == 'dev'
Provides-Extra: docs
Requires-Dist: sphinx; extra == 'docs'
Provides-Extra: plot
Requires-Dist: matplotlib; extra == 'plot'
Provides-Extra: test
Requires-Dist: pytest; extra == 'test'
Requires-Dist: pytest-runner; extra == 'test'
Requires-Dist: flake8; extra == 'test'
Provides-Extra: tf
Requires-Dist: tensorflow (>=1.1.0); extra == 'tf'
Provides-Extra: tf_gpu
Requires-Dist: tensorflow-gpu (>=1.1.0); extra == 'tf_gpu'
